ipynb_creative/__init__.py
ipynb_creative/_version.py
ipynb_creative/labextension/build_log.json
ipynb_creative/labextension/package.json
ipynb_creative/labextension/static/lib_index_js.559f44206b73afdc4814.js
ipynb_creative/labextension/static/lib_index_js.559f44206b73afdc4814.js.map
ipynb_creative/labextension/static/remoteEntry.faf93573e3e62bcb8188.js
ipynb_creative/labextension/static/remoteEntry.faf93573e3e62bcb8188.js.map
ipynb_creative/labextension/static/style.js
ipynb_creative/labextension/static/style_index_js.35c60011f709362e67ed.js
ipynb_creative/labextension/static/style_index_js.35c60011f709362e67ed.js.map
ipynb_creative/labextension/static/vendors-node_modules_axios_index_js.d1acbb4ebd88645e5086.js
ipynb_creative/labextension/static/vendors-node_modules_axios_index_js.d1acbb4ebd88645e5086.js.map
ipynb_creative/labextension/static/vendors-node_modules_css-loader_dist_runtime_api_js-node_modules_css-loader_dist_runtime_cssW-72eba1.e1b3ac7f56a1d352903d.js
ipynb_creative/labextension/static/vendors-node_modules_css-loader_dist_runtime_api_js-node_modules_css-loader_dist_runtime_cssW-72eba1.e1b3ac7f56a1d352903d.js.map
omoujan/__init__.py
omoujan/_version.py
omoujan/labextension/build_log.json
omoujan/labextension/package.json
omoujan/labextension/static/lib_index_js.0f0a6ac7f9cef4c39dfc.js
omoujan/labextension/static/lib_index_js.0f0a6ac7f9cef4c39dfc.js.map
omoujan/labextension/static/lib_index_js.5ce85bb3b94a183fdc61.js
omoujan/labextension/static/lib_index_js.5ce85bb3b94a183fdc61.js.map
omoujan/labextension/static/remoteEntry.734a7aa2f70d18c63fd0.js
omoujan/labextension/static/remoteEntry.734a7aa2f70d18c63fd0.js.map
omoujan/labextension/static/remoteEntry.a44e42fc26a1728b0c63.js
omoujan/labextension/static/remoteEntry.a44e42fc26a1728b0c63.js.map
omoujan/labextension/static/remoteEntry.b6bb9b2d66ab4b023234.js
omoujan/labextension/static/remoteEntry.b6bb9b2d66ab4b023234.js.map
omoujan/labextension/static/remoteEntry.e9790556d8f2c8e98829.js
omoujan-0.1.1.dist-info/LICENSE
omoujan-0.1.1.dist-info/METADATA
omoujan-0.1.1.dist-info/WHEEL
omoujan-0.1.1.dist-info/entry_points.txt
omoujan-0.1.1.dist-info/top_level.txt
omoujan-0.1.1.dist-info/RECORD
